[
  {
    "key": "pb_phase0_opening_002",
    "phase": "0",
    "type": "OPENING",
    "customerSegment": "ALL",
    "trigger": null,
    "script": "15분 안에 '이건 나한테 필요 없다' 싶으시면 제가 먼저 전화 끊겠습니다. 괜찮으세요?",
    "psychology": "Loss Aversion (Kahneman)",
    "notes": "신민형 STEP 1: 주도권 탈취. 고객에게 통제권 복원으로 방어막 해제",
    "isActive": true
  },
  {
    "key": "pb_phase0_opening_008",
    "phase": "0",
    "type": "OPENING",
    "customerSegment": "ALL",
    "trigger": null,
    "script": "요즘 크루즈 여행 많이 가고 있는 거 알고 계시죠? 자녀 객실 6개 남아 있는 상황이고요. 특가 혜택이 마감이 빨리 되기 때문에 제가 신속하게 안내를 도와드릴 텐데요.",
    "psychology": "Scarcity (Cialdini)",
    "notes": "수량 + 시간 희소성 동시 제시. 구체적 수치(6개)로 신뢰성 상승",
    "isActive": true
  },
  {
    "key": "pb_phase0_opening_012",
    "phase": "0",
    "type": "OPENING",
    "customerSegment": "ALL",
    "trigger": null,
    "script": "지금 네이버에 '크루즈닷 사업자등록번호 714-57-00419' 검색해 보세요. 신한은행이 준비금을 보관한다는 게 사기 업체가 할 수 있는 구조일까요?",
    "psychology": "Social Proof (Cialdini)",
    "notes": "즉각적 검증 권유. 신한은행이라는 제3자 기관의 권위 활용. 신뢰도 최상",
    "isActive": true
  },
  {
    "key": "pb_phase0_opening_013",
    "phase": "0",
    "type": "OPENING",
    "customerSegment": "ALL",
    "trigger": null,
    "script": "저희 3,000명 손님 중에서 멀미로 못 즐기셨다는 분이 거의 없어요. 혹시 제가 멀미 예방법도 카톡으로 보내드릴까요?",
    "psychology": "Social Proof (Cialdini)",
    "notes": "대수 통계(3,000명)로 신뢰성 강화. 우려 사항 즉시 해소",
    "isActive": true
  },
  {
    "key": "pb_phase0_opening_014",
    "phase": "0",
    "type": "OPENING",
    "customerSegment": "ALL",
    "trigger": null,
    "script": "우리나라에서 한 1%밖에 안 가봤어요. 이번에 갔다 오시면 또래 분들보다 최고의 추억이 될 거예요.",
    "psychology": "Scarcity (Cialdini)",
    "notes": "1% 희소성으로 프리미엄 경험감 극대화. 또래 비교로 특별성 강조",
    "isActive": true
  },
  {
    "key": "pb_phase0_opening_015",
    "phase": "0",
    "type": "OPENING",
    "customerSegment": "ALL",
    "trigger": null,
    "script": "보니까 크루즈 처음이라고 하셨어요. 혹시 뭐 어떤 사연 아니면 이벤트 계기 이런 게 있어서 크루즈 여행 계획하시는 걸까요?",
    "psychology": "Narrative Transportation (Green & Brock)",
    "notes": "고객의 진정한 욕망 계기 파악. 감정적 연결 고리 찾기",
    "isActive": true
  },
  {
    "key": "pb_phase0_opening_020",
    "phase": "0",
    "type": "OPENING",
    "customerSegment": "ALL",
    "trigger": null,
    "script": "지금 혜영님도 그렇고 기현님도 그렇고 크루즈 아직 한 번 안 타보신 거죠? 그러면 저희가 몇 가지 체크를 해야 해서 이렇게 신청하기 대신 계기를 먼저 좀 여쭤봐도 될까요?",
    "psychology": "Priming (Implicit Memory)",
    "notes": "초보자 인식 후 개인화된 설명 준비. 상황 파악으로 맞춤형 제안 가능",
    "isActive": true
  },
  {
    "key": "pb_phase1_needs_spin_001",
    "phase": "1",
    "type": "NEEDS",
    "customerSegment": "ALL",
    "trigger": null,
    "script": "어머니, 살면서 가장 가고 싶으셨던 나라가 어디예요?",
    "psychology": "Narrative Transportation (Green & Brock)",
    "notes": "SPIN S단계. 고객의 깊은 욕망을 스스로 표현하게 유도",
    "isActive": true
  },
  {
    "key": "pb_phase1_needs_spin_003",
    "phase": "1",
    "type": "NEEDS",
    "customerSegment": "ALL",
    "trigger": null,
    "script": "어머니, 혹시 지금 고민하시는 게 뭔지 여쭤봐도 될까요? 가격 문제인가요, 아니면 구조가 이해가 안 되시는 건가요?",
    "psychology": "Status Quo Bias",
    "notes": "SPIN I단계. 현재 장벽을 3초 침묵 후 명확하게 정의",
    "isActive": true
  },
  {
    "key": "pb_phase1_needs_spin_004",
    "phase": "1",
    "type": "NEEDS",
    "customerSegment": "ALL",
    "trigger": null,
    "script": "어머니, 무릎이나 허리는 괜찮으세요? 크루즈가 다른 여행이랑 다른 게, 짐을 한 번만 풀면 여러 나라를 다니거든요.",
    "psychology": "Commitment & Consistency (Cialdini)",
    "notes": "SPIN P단계(문제). 신민형 STEP 2: 비교기준 설정. 건강 상태 자연스럽게 파악",
    "isActive": true
  },
  {
    "key": "pb_phase1_needs_spin_005",
    "phase": "1",
    "type": "NEEDS",
    "customerSegment": "ALL",
    "trigger": null,
    "script": "어머니, 혹시 마지막으로 배 타신 게 언제예요? 요즘 크루즈 배가 얼마나 큰지 아세요?",
    "psychology": "Priming (Implicit Memory)",
    "notes": "멀미 공포를 건설적으로 재구성. 현대 선박 크기로 안전감 제공",
    "isActive": true
  },
  {
    "key": "pb_phase1_needs_spin_006",
    "phase": "1",
    "type": "NEEDS",
    "customerSegment": "ALL",
    "trigger": null,
    "script": "어머니, 혼자 가시는 게 무서우신 게 언어 문제인가요, 아니면 같이 있을 사람이 없어서인가요?",
    "psychology": "Status Quo Bias",
    "notes": "SPIN I단계 심화. 불안 유형 세분화로 맞춤형 해결책 제시",
    "isActive": true
  },
  {
    "key": "pb_phase1_needs_spin_007",
    "phase": "1",
    "type": "NEEDS",
    "customerSegment": "ALL",
    "trigger": null,
    "script": "어머니, 유럽이나 지중해는 가보셨어요? 아니면 어디 가보고 싶으신 데가 있으세요?",
    "psychology": "Loss Aversion (Kahneman)",
    "notes": "숨겨진 욕망 파악. 실현 가능성 확인으로 Implication 도출",
    "isActive": true
  },
  {
    "key": "pb_phase1_needs_spin_014",
    "phase": "1",
    "type": "NEEDS",
    "customerSegment": "ALL",
    "trigger": null,
    "script": "크루즈 타보셨어요? 어디 가셨어요?",
    "psychology": "Narrative Transportation (Green & Brock)",
    "notes": "크루즈 경험자용 분기. 과거 경험의 약점을 크루즈 강점으로 전환",
    "isActive": true
  },
  {
    "key": "pb_phase2_amplify_003",
    "phase": "2",
    "type": "AMPLIFY",
    "customerSegment": "ALL",
    "trigger": null,
    "script": "선생님, 시간도 비용도 아무 제한이 없다면 홍콩 마카오를 어떻게 즐기고 싶으세요? 그냥 패키지로 빡빡하게요, 아니면 럭셔리하게 여유롭게요?",
    "psychology": "Loss Aversion (Kahneman)",
    "notes": "모니카 욕망깨우기. 현재→최상 상태 프레임 전환. 럭셔리 욕망 극대화",
    "isActive": true
  },
  {
    "key": "pb_phase2_amplify_004",
    "phase": "2",
    "type": "AMPLIFY",
    "customerSegment": "ALL",
    "trigger": null,
    "script": "누구나 다 돈이 많으면 럭셔리 당연 가고 싶잖아요. 1000만원짜리 크루즈 당연 타고 싶지. 그걸 욕망을 불러일으켜줘야 해요 — 그게 현실이 될 수 있다는 거.",
    "psychology": "Narrative Transportation (Green & Brock)",
    "notes": "신민형 STEP 1: 주도권 탈취 + 욕망 정당화. 럭셔리는 보편적 욕망임을 강조",
    "isActive": true
  },
  {
    "key": "pb_phase2_amplify_005",
    "phase": "2",
    "type": "AMPLIFY",
    "customerSegment": "ALL",
    "trigger": null,
    "script": "홍콩 좋아하세요! 어떤 부분이 제일 좋으세요? 야경이에요, 음식이에요?",
    "psychology": "Priming (Implicit Memory)",
    "notes": "모니카 프리미엄인식. 일반적 욕망→구체적 욕망으로 심화. 5감각 앵커링 준비",
    "isActive": true
  },
  {
    "key": "pb_phase2_amplify_006",
    "phase": "2",
    "type": "AMPLIFY",
    "customerSegment": "ALL",
    "trigger": null,
    "script": "맞아요, 홍콩이 그래서 자꾸 가고 싶잖아요. 선생님, 말씀하신 그 여행이 어떻게 실현될 수 있을까 한 번 생각해봐도 될까요?",
    "psychology": "Commitment & Consistency (Cialdini)",
    "notes": "욕망→현실 가능성으로 프레임 전환. 행동 유도 전단계",
    "isActive": true
  },
  {
    "key": "pb_phase2_amplify_007",
    "phase": "2",
    "type": "AMPLIFY",
    "customerSegment": "ALL",
    "trigger": null,
    "script": "지금 1년에 한 번도 여행 못 가시면, 10년이면 10번이에요. 60대에 10번이 없으면... 그 기억들이 다 없어지는 거잖아요.",
    "psychology": "Loss Aversion (Kahneman)",
    "notes": "신민형 STEP 3: 손실앵커 1레이어. 즉각 손실. 시간의 유한성 강조",
    "isActive": true
  },
  {
    "key": "pb_phase2_amplify_008",
    "phase": "2",
    "type": "AMPLIFY",
    "customerSegment": "ALL",
    "trigger": null,
    "script": "그 돈으로 여행 갈 수 있는데, 지금 안 쓰시면 언제 쓰실 거예요? 특히 건강이 좋을 때.",
    "psychology": "Status Quo Bias",
    "notes": "신민형 STEP 3: 손실앵커 2-3레이어. 기회비용 + 체력 창문",
    "isActive": true
  },
  {
    "key": "pb_phase2_amplify_009",
    "phase": "2",
    "type": "AMPLIFY",
    "customerSegment": "ALL",
    "trigger": null,
    "script": "어머니가 이런 여행 못 가시면 따님이 나중에 뭐라고 할까요? '엄마, 당신 시대에 왜 못 갔어?' 이렇게 안 할까요?",
    "psychology": "Loss Aversion (Kahneman)",
    "notes": "신민형 STEP 3: 손실앵커 4레이어. 자녀 인정 욕구 손실. 5060 여성 최강 트리거",
    "isActive": true
  },
  {
    "key": "pb_phase2_amplify_010",
    "phase": "2",
    "type": "AMPLIFY",
    "customerSegment": "ALL",
    "trigger": null,
    "script": "10년 후에 이 순간을 후회하실 거예요. '그때 갈 걸' 이러는 분들 많거든요.",
    "psychology": "Loss Aversion (Kahneman)",
    "notes": "신민형 STEP 3: 손실앵커 5레이어. 기억 손실의 영구성. 지금 결정의 중요성",
    "isActive": true
  },
  {
    "key": "pb_phase2_amplify_011",
    "phase": "2",
    "type": "AMPLIFY",
    "customerSegment": "ALL",
    "trigger": null,
    "script": "어머니는 어떤 사람으로 기억되고 싶어요? 남편분이나 자녀들한테?",
    "psychology": "Narrative Transportation (Green & Brock)",
    "notes": "신민형 STEP 3: 손실앵커 6레이어. 정체성 질문. 깊은 욕망 수준으로 상승",
    "isActive": true
  },
  {
    "key": "pb_phase2_amplify_012",
    "phase": "2",
    "type": "AMPLIFY",
    "customerSegment": "ALL",
    "trigger": null,
    "script": "지금 좀 더 생각해볼게요.",
    "script_response": "그러니까요. 그래서 오늘 연락드린 거예요. 저도 좀 더 생각하다가 놓친 분들 몇 분 봤거든요.",
    "psychology": "Loss Aversion (Kahneman)",
    "notes": "신민형 STEP 3: 손실앵커 반론처리. 에이킨 법칙. 생각을 인정하되 지금의 중요성",
    "isActive": true
  },
  {
    "key": "pb_phase2_amplify_013",
    "phase": "2",
    "type": "AMPLIFY",
    "customerSegment": "ALL",
    "trigger": null,
    "script": "선생님, 잠깐 정리 좀 해도 될까요? 선생님이 원하시는 게 뭔지 제가 정확히 파악해야 제대로 설계해드릴 수 있거든요. 홍콩 마카오를 어떻게 즐기고 싶으신 거예요? 딱 하나만요.",
    "psychology": "Commitment & Consistency (Cialdini)",
    "notes": "RESET 패턴. 욕망 증폭 재진입. 대화가 핑퐁할 때 원점 복귀",
    "isActive": true
  },
  {
    "key": "pb_phase3_positioning_001",
    "phase": "3",
    "type": "POSITIONING",
    "customerSegment": "ALL",
    "trigger": null,
    "script": "산토리니 이야기 하셨잖아요. 잠깐 상상해보실래요? 파란 지붕 위에 서 계시는 거예요 — 눈에 들어오는 에게해.",
    "psychology": "Narrative Transportation (Green & Brock)",
    "notes": "모니카 비교기준 설정. 5감각 첫 번째: 시각. 구체적 장면 그리기로 상상 현실화",
    "isActive": true
  },
  {
    "key": "pb_phase3_positioning_002",
    "phase": "3",
    "type": "POSITIONING",
    "customerSegment": "ALL",
    "trigger": null,
    "script": "석양이 지는데 바람이 딱 살짝 불어요.",
    "psychology": "Narrative Transportation (Green & Brock)",
    "notes": "5감각 두 번째: 촉각. 물리적 감각으로 몰입도 증가",
    "isActive": true
  },
  {
    "key": "pb_phase3_positioning_003",
    "phase": "3",
    "type": "POSITIONING",
    "customerSegment": "ALL",
    "trigger": null,
    "script": "거기서 소금기 있는 바다 냄새가 나고요.",
    "psychology": "Priming (Implicit Memory)",
    "notes": "5감각 세 번째: 후각. 감각의 진정성 높음",
    "isActive": true
  },
  {
    "key": "pb_phase3_positioning_004",
    "phase": "3",
    "type": "POSITIONING",
    "customerSegment": "ALL",
    "trigger": null,
    "script": "파도 소리랑 멀리서 그리스 음악이 들리고.",
    "psychology": "Priming (Implicit Memory)",
    "notes": "5감각 네 번째: 청각. 배경음의 심리적 효과 최강",
    "isActive": true
  },
  {
    "key": "pb_phase3_positioning_005",
    "phase": "3",
    "type": "POSITIONING",
    "customerSegment": "ALL",
    "trigger": null,
    "script": "그날 저녁에 신선한 올리브랑 와인 한 잔 하시는 거예요.",
    "psychology": "Narrative Transportation (Green & Brock)",
    "notes": "5감각 다섯 번째: 미각. 럭셔리 경험의 정점",
    "isActive": true
  },
  {
    "key": "pb_phase3_positioning_006",
    "phase": "3",
    "type": "POSITIONING",
    "customerSegment": "ALL",
    "trigger": null,
    "script": "그때 옆에 누구랑 가고 싶으세요?",
    "psychology": "Loss Aversion (Kahneman)",
    "notes": "5감각 후 침묵(3초). 고객이 동반자를 상상하게 함. 자녀 언급 유도",
    "isActive": true
  },
  {
    "key": "pb_phase3_positioning_007",
    "phase": "3",
    "type": "POSITIONING",
    "customerSegment": "ALL",
    "trigger": null,
    "script": "아드님/따님이 '엄마 진짜 잘 다녀오셨다' 하실 것 같지 않으세요?",
    "psychology": "Loss Aversion (Kahneman)",
    "notes": "가족감성. 5060 최강 트리거: 자녀 인정. 자신의 가치를 자녀가 인정하는 장면",
    "isActive": true
  },
  {
    "key": "pb_phase3_positioning_008",
    "phase": "3",
    "type": "POSITIONING",
    "customerSegment": "ALL",
    "trigger": null,
    "script": "너무 친절하게 설명해주셔서 지금 가 있는 거 같잖아요, 거기.",
    "psychology": "Commitment & Consistency (Cialdini)",
    "notes": "상상 현실화. 고객이 이미 마음으로 여행을 가는 상태",
    "isActive": true
  },
  {
    "key": "pb_phase3_positioning_009",
    "phase": "3",
    "type": "POSITIONING",
    "customerSegment": "ALL",
    "trigger": null,
    "script": "아메리카노 한 잔 값으로 산토리니 석양을 볼 수 있다고 상상해보세요. 하루 1,100원이면 커피 한 잔이잖아요.",
    "psychology": "Priming (Implicit Memory)",
    "notes": "신민형 STEP 2: 비교기준. 일일 비용을 생활 필수품으로 재프레이밍. 거부감 제거",
    "isActive": true
  },
  {
    "key": "pb_phase3_positioning_010",
    "phase": "3",
    "type": "POSITIONING",
    "customerSegment": "ALL",
    "trigger": null,
    "script": "커피 한 잔을 참으시면 크루즈 가시는 거예요.",
    "psychology": "Commitment & Consistency (Cialdini)",
    "notes": "포기 vs 크루즈의 간단한 선택지. 행동 지향적",
    "isActive": true
  },
  {
    "key": "pb_phase3_positioning_011",
    "phase": "3",
    "type": "POSITIONING",
    "customerSegment": "ALL",
    "trigger": null,
    "script": "무릎이 좋을 때가 창문이에요. 지금 몸이 허락할 때 가셔야 제대로 즐기실 수 있어요.",
    "psychology": "Loss Aversion (Kahneman)",
    "notes": "체력 창문. 신민형 STEP 3: 손실앵커. 건강을 시간 제한된 자원으로 프레이밍",
    "isActive": true
  },
  {
    "key": "pb_phase3_positioning_015",
    "phase": "3",
    "type": "POSITIONING",
    "customerSegment": "ALL",
    "trigger": null,
    "script": "크루즈가 일반 여행이랑 다른 게, 짐을 한 번만 풀어요. 그리스, 이탈리아, 터키를 일반 여행으로 가시면 짐을 5번 풀어야 하거든요.",
    "psychology": "Status Quo Bias",
    "notes": "차별점. 구체적 숫자(5번)로 크루즈의 편리함 강조. 경험 질 개선",
    "isActive": true
  },
  {
    "key": "pb_phase3_positioning_016",
    "phase": "3",
    "type": "POSITIONING",
    "customerSegment": "ALL",
    "trigger": null,
    "script": "여행 많이 다니신 분들이 크루즈 한 번 타고 나면 다시는 패키지 안 가신다고 하세요.",
    "psychology": "Social Proof (Cialdini)",
    "notes": "신민형 STEP 2: 비교기준 설정. 많은 경험을 가진 고객들의 선택",
    "isActive": true
  },
  {
    "key": "pb_phase3_positioning_019",
    "phase": "3",
    "type": "POSITIONING",
    "customerSegment": "ALL",
    "trigger": null,
    "script": "저를 믿는 게 아니라 신한은행을 믿으시는 거예요.",
    "psychology": "Social Proof (Cialdini)",
    "notes": "안전성. 상담사 신뢰가 아닌 기관 신뢰로 객관성 강화",
    "isActive": true
  },
  {
    "key": "pb_phase4_closing_001",
    "phase": "8",
    "type": "CLOSING",
    "customerSegment": "ALL",
    "trigger": null,
    "script": "언제까지 결정하면 돼요?",
    "script_response": "지금 바로 가능하세요?",
    "psychology": "Loss Aversion (Kahneman)",
    "notes": "신민형 STEP 4: 삼중선택. 클로징 신호 탐지. 고객이 시간 제한을 물으면 욕망 신호",
    "isActive": true
  },
  {
    "key": "pb_phase4_closing_002",
    "phase": "8",
    "type": "CLOSING",
    "customerSegment": "ALL",
    "trigger": null,
    "script": "지금 바로 결정 안 하셔도 돼요. 제가 오늘 고객님 자리만 먼저 확보해드릴게요. 3일 안에 변경하시거나 취소하셔도 돼요.",
    "psychology": "Loss Aversion (Kahneman)",
    "notes": "모니카 클로징. 소프트 클로즈. 자리 확보로 심리적 소유감. 위험 제거",
    "isActive": true
  },
  {
    "key": "pb_phase4_closing_003",
    "phase": "8",
    "type": "CLOSING",
    "customerSegment": "ALL",
    "trigger": null,
    "script": "일단 자리 잡혀있는 게 마음이 편하시잖아요.",
    "psychology": "Status Quo Bias",
    "notes": "심리적 소유감 형성. 취소 확률 낮춤",
    "isActive": true
  },
  {
    "key": "pb_phase4_closing_004",
    "phase": "8",
    "type": "CLOSING",
    "customerSegment": "ALL",
    "trigger": null,
    "script": "그렇게 하면 내일 바로 결정이 되고, 이튿날에 좀 더 생각해 본 다음에 최종 결정하는 것도 가능해요. 아니면 지금 바로 해도 되고요.",
    "psychology": "Commitment & Consistency (Cialdini)",
    "notes": "신민형 STEP 4: 삼중선택(지금/내일/이튿날). 선택지 2개로 선택 강박 완화",
    "isActive": true
  },
  {
    "key": "pb_phase4_closing_005",
    "phase": "8",
    "type": "CLOSING",
    "customerSegment": "ALL",
    "trigger": null,
    "script": "어떻게 시작하면 돼요?",
    "script_response": "제가 안내해드릴게요. 지금 간단한 정보만 3개 여쭤볼게요.",
    "psychology": "Commitment & Consistency (Cialdini)",
    "notes": "신민형 STEP 5: 즉시클로징. 고객이 실행 방법을 물으면 내적 결정 완료 신호",
    "isActive": true
  },
  {
    "key": "pb_phase4_closing_006",
    "phase": "8",
    "type": "CLOSING",
    "customerSegment": "ALL",
    "trigger": null,
    "script": "○○하면 어떡해요?",
    "script_response": "좋은 질문이세요. 그래도 전혀 문제 안 돼요. [해결 방법].",
    "psychology": "Loss Aversion (Kahneman)",
    "notes": "클로징 가정 자체가 긍정 신호. 즉시 우려 해소로 최종 결정 완성",
    "isActive": true
  },
  {
    "key": "pb_phase4_closing_007",
    "phase": "8",
    "type": "CLOSING",
    "customerSegment": "ALL",
    "trigger": null,
    "script": "언제 출발 가능해요?",
    "script_response": "고객님 일정 먼저 여쭤볼게요. 언제 가장 괜찮으신가요?",
    "psychology": "Commitment & Consistency (Cialdini)",
    "notes": "신민형 STEP 5: 즉시클로징. 출발일 질문은 강한 긍정 신호",
    "isActive": true
  },
  {
    "key": "pb_phase4_closing_008",
    "phase": "8",
    "type": "CLOSING",
    "customerSegment": "ALL",
    "trigger": null,
    "script": "선착순 50인 중 37명이 벌써 예약을 해버려가지고...",
    "psychology": "Scarcity (Cialdini)",
    "notes": "희소성 구체화. 실시간 수치로 신뢰도 상승",
    "isActive": true
  },
  {
    "key": "pb_phase4_closing_009",
    "phase": "8",
    "type": "CLOSING",
    "customerSegment": "ALL",
    "trigger": null,
    "script": "이번 달 말까지 모집이에요.",
    "psychology": "Scarcity (Cialdini)",
    "notes": "시간 희소성. 1차 데드라인",
    "isActive": true
  },
  {
    "key": "pb_phase4_closing_010",
    "phase": "8",
    "type": "CLOSING",
    "customerSegment": "ALL",
    "trigger": null,
    "script": "남은 자리가 ○자리예요.",
    "psychology": "Scarcity (Cialdini)",
    "notes": "수량 희소성. 2차 데드라인. 시간+수량 희소성 동시 제시",
    "isActive": true
  },
  {
    "key": "pb_phase4_closing_014",
    "phase": "8",
    "type": "CLOSING",
    "customerSegment": "ALL",
    "trigger": null,
    "script": "저도 12월 크루즈 갈 예정이에요.",
    "psychology": "Social Proof (Cialdini)",
    "notes": "상담사도 고객 입장에서 구매. 가장 강력한 신뢰 신호",
    "isActive": true
  },
  {
    "key": "pb_phase5_objection_001",
    "phase": "objection",
    "type": "OBJECTION",
    "customerSegment": "ALL",
    "trigger": "비싸요",
    "script": "네, 처음 들으시면 비싸게 느껴지시죠. 당연해요. 크루즈 하면 럭셔리 이미지가 있으니까요. 어머니, 혹시 일반 패키지 여행 가시면 보통 얼마 드세요?",
    "psychology": "Loss Aversion (Kahneman)",
    "notes": "신민형 STEP 2: 비교기준 설정. 가격을 커피로 재프레이밍",
    "isActive": true
  },
  {
    "key": "pb_phase5_objection_002",
    "phase": "objection",
    "type": "OBJECTION",
    "customerSegment": "ALL",
    "trigger": "사기 같아요",
    "script": "맞아요, 요즘 세상에 의심하시는 게 너무 당연해요. 저도 어머니 입장이라면 똑같이 의심했을 거예요. 그런데 어머니, 사기인지 아닌지 확인하는 가장 빠른 방법이 뭔지 아세요?",
    "psychology": "Social Proof (Cialdini)",
    "notes": "신한은행 신탁 계좌와 사업자등록번호로 기관 권위 검증",
    "isActive": true
  },
  {
    "key": "pb_phase5_objection_003",
    "phase": "objection",
    "type": "OBJECTION",
    "customerSegment": "ALL",
    "trigger": "생각해볼게요",
    "script": "네, 물론이죠. 이런 결정 바로 하시기 어렵죠. 충분히 이해해요. 어머니, 혹시 지금 고민하시는 게 뭔지 여쭤봐도 될까요?",
    "psychology": "Status Quo Bias",
    "notes": "진짜 이유 파악 후 재연락 약속. 즉각 클로징 강요 금지",
    "isActive": true
  },
  {
    "key": "pb_phase5_objection_004",
    "phase": "objection",
    "type": "OBJECTION",
    "customerSegment": "ALL",
    "trigger": "남편이 반대해요",
    "script": "아, 남편분이 처음에 다들 반대하세요. 낯선 구조이니까요. 당연해요. 남편분이 반대하시는 이유가 정확히 뭔지 아세요?",
    "psychology": "Commitment & Consistency (Cialdini)",
    "notes": "남편을 세일즈맨으로 만들기. 직접 설명 요청으로 전환",
    "isActive": true
  },
  {
    "key": "pb_phase5_objection_005",
    "phase": "objection",
    "type": "OBJECTION",
    "customerSegment": "ALL",
    "trigger": "나중에 해도 되잖아요",
    "script": "맞아요, 여행은 언제든 갈 수 있죠. 어머니, 혹시 무릎이나 허리는 괜찮으세요? 크루즈가 다른 여행이랑 다른 게, 짐을 한 번만 풀면 여러 나라를 다니거든요.",
    "psychology": "Loss Aversion (Kahneman)",
    "notes": "신민형 STEP 3: 손실앵커. 무릎이 좋을 때 = 창문이 열려 있는 상태",
    "isActive": true
  },
  {
    "key": "pb_phase5_objection_007",
    "phase": "objection",
    "type": "OBJECTION",
    "customerSegment": "ALL",
    "trigger": "멀미가 심해요",
    "script": "아, 멀미 걱정 많이 하세요. 옛날에 배 타셨다가 고생하신 분들이 많거든요. 어머니, 혹시 마지막으로 배 타신 게 언제예요?",
    "psychology": "Priming (Implicit Memory)",
    "notes": "현대 크루즈는 축구장 3개 크기. 63빌딩이 바다 위에 떠 있는 것",
    "isActive": true
  },
  {
    "key": "pb_phase5_objection_008",
    "phase": "objection",
    "type": "OBJECTION",
    "customerSegment": "ALL",
    "trigger": "혼자 가기 무서워요",
    "script": "혼자 가시는 거 무서우시죠. 처음엔 다 그러세요. 어머니, 혼자 가시는 게 무서우신 게 언어 문제인가요, 아니면 같이 있을 사람이 없어서인가요?",
    "psychology": "Status Quo Bias",
    "notes": "장벽 세분화. 11년 경력 인솔자 + 단체 여행 + 자연스러운 친구 형성",
    "isActive": true
  },
  {
    "key": "pb_phase5_objection_009",
    "phase": "objection",
    "type": "OBJECTION",
    "customerSegment": "ALL",
    "trigger": "카톡으로 보내주세요",
    "script": "네, 보내드릴게요. 당연하죠. 그런데 어머니, 카톡 보내드리면 보시고 궁금하신 게 생기실 수 있잖아요. 그때 제가 바로 답해드릴 수 있게 한 가지만 여쭤볼게요.",
    "psychology": "Commitment & Consistency (Cialdini)",
    "notes": "카톡 요청은 관심 신호. 다음 약속 필수. 거절이 아님",
    "isActive": true
  },
  {
    "key": "pb_phase5_objection_010",
    "phase": "objection",
    "type": "OBJECTION",
    "customerSegment": "ALL",
    "trigger": "이미 여행 잘 다녀요",
    "script": "어머니, 여행을 많이 다니셨군요. 그럼 여행이 얼마나 좋은지 잘 아시겠네요. 혹시 유럽이나 지중해는 가보셨어요?",
    "psychology": "Loss Aversion (Kahneman)",
    "notes": "짐 한 번만 풀기. 많이 다녀본 사람일수록 크루즈 선호",
    "isActive": true
  },
  {
    "key": "pb_phase6_followup_002",
    "phase": "followup",
    "type": "FOLLOWUP",
    "customerSegment": "ALL",
    "trigger": "2차 콜 오프닝 (24~48시간)",
    "script": "어머니, 저 어제 통화했던 [이름]이에요. 카톡 보셨어요? [여행지] 사진 예쁘죠? 어머니 가시면 딱 그 뷰에서 사진 찍어드릴 수 있거든요. 잠깐 얘기 괜찮으세요?",
    "psychology": "Narrative Transportation (Green & Brock)",
    "notes": "Day 1-2: 신뢰 연속성. 이미지 앵커로 재활성화. 짧은 시간 요청",
    "isActive": true
  },
  {
    "key": "pb_phase6_followup_003",
    "phase": "followup",
    "type": "FOLLOWUP",
    "customerSegment": "ALL",
    "trigger": "2차 콜 중 (24~48시간)",
    "script": "선생님, 저번에 홍콩 야경 보면서 저녁 먹고 싶다고 하셨잖아요. 그 얘기 생각나세요? 그게 지금 가능해요.",
    "psychology": "Priming (Implicit Memory)",
    "notes": "망각 곡선 리마인드. 고객의 욕망을 그대로 반영. 욕망 재활성화",
    "isActive": true
  },
  {
    "key": "pb_phase6_followup_004",
    "phase": "followup",
    "type": "FOLLOWUP",
    "customerSegment": "ALL",
    "trigger": "2차 콜 중 저항",
    "script": "내일 이 시간에 제가 연락드려도 될까요? 카톡 보시고 나서 궁금하신 거 같이 얘기해보면 어떨까요? 5분이면 돼요.",
    "psychology": "Loss Aversion (Kahneman)",
    "notes": "다음 약속 확정. 망각곡선 회피. 재연락 필수",
    "isActive": true
  },
  {
    "key": "pb_phase6_followup_009",
    "phase": "followup",
    "type": "FOLLOWUP",
    "customerSegment": "ALL",
    "trigger": "재콜 Day 3",
    "script": "[오프닝 생략]\n\n어머니, 참고로 이번 달까지 40% 할인인데, 다음 달이면 할인이 30%로 줄어들어요. 어머니는 어떻게 생각하세요?",
    "psychology": "Scarcity (Cialdini)",
    "notes": "Day 3: 희소성 재부각. 가격이 올라가는 것을 명확히 함",
    "isActive": true
  },
  {
    "key": "pb_phase6_followup_010",
    "phase": "followup",
    "type": "FOLLOWUP",
    "customerSegment": "ALL",
    "trigger": "재콜 Day 7",
    "script": "[오프닝 생략]\n\n어머니, 저희 이전 고객분들 중에 '그 시간에 할 걸' 이러는 분들이 꽤 많거든요. 그래서 그냥 자리 확보해 드리고 싶은데 괜찮으세요?",
    "psychology": "Social Proof (Cialdini)",
    "notes": "Day 7: 사회적 증거로 FOMO 유도. 자리 확보로 심리적 소유감 형성",
    "isActive": true
  },
  {
    "key": "pb_bonus_opener_002",
    "phase": "0",
    "type": "OPENING",
    "customerSegment": "A|B",
    "trigger": null,
    "script": "저희 고객들 중에서 가장 만족도가 높은 분들이 누구 아세요? 자녀분들을 위해서 가신 분들보다 본인 자신을 위해서 가신 분들이에요.",
    "psychology": "Loss Aversion (Kahneman)",
    "notes": "세그먼트 A/B(자녀중심): 자신의 가치 강조. 정체성 승격",
    "isActive": true
  },
  {
    "key": "pb_bonus_value_001",
    "phase": "3",
    "type": "POSITIONING",
    "customerSegment": "ALL",
    "trigger": null,
    "script": "결국 돈이 많고 적은 게 중요한 게 아니라, 어떻게 쓰냐가 중요한 거예요.",
    "psychology": "Commitment & Consistency (Cialdini)",
    "notes": "가치 재정의. 부의 문제를 사용법으로 전환. 모든 소득 대역에 공감",
    "isActive": true
  },
  {
    "key": "pb_bonus_value_002",
    "phase": "3",
    "type": "POSITIONING",
    "customerSegment": "ALL",
    "trigger": null,
    "script": "집에서 편히 쉬는 것도 좋지만, 배 위에서 바다를 보면서 쉬는 게 한 번은 경험해 보는 거 어때요?",
    "psychology": "Status Quo Bias",
    "notes": "일상 vs 크루즈의 가치 비교. 자연스러운 선택지 제시",
    "isActive": true
  }
]
