{
  "file_name": "인스타그램마케팅이막막한분들을위한핵심노하우소책자-가이드추가버전.pdf",
  "setup_strategy": [
    "계정유형: 비즈니스 계정으로 전환 (크루즈닷 공식계정 + 지사별 서브계정 구분)",
    "프로필최적화: 명확한 가치제안 + 클릭유도(예: '크루즈 상담 링크 bio에 배치') + 프로필사진(로고/대표상품)",
    "초기팔로워빌드: 경험많은 여행자 커뮤니티 페이지와 팔로우/댓글/공유로 관계형성",
    "지사별계층화: 본사계정(전국)+지사계정(지역) 구분으로 지역밀착 마케팅 강화",
    "북마크액션설정: 프로필 링크 클릭시 랜딩페이지(크루즈상품소개) 바로연결"
  ],
  "content_types": [
    "릴스(Reels): 15-30초 크루즈선박 항공뷰/승선장면/해양스포츠/디너뷰 숏폼 콘텐츠(매일 1개)",
    "캐러셀(Carousel): 5-7장 여행일정 슬라이드(Day1-Day5 크루즈일정/기항지/식사/가격공시)",
    "스토리(Stories): 24시간 한시간주기로 타임딜/한정상품/고객후기/Q&A 라이브감 전달",
    "게시물(Feed): 주3회 해양문화/기항지정보/승객인터뷰/시즈널특가 교육적콘텐츠",
    "라이브방송(Live): 주1회 선사담당자/전국지사장 라이브 Q&A(금요일저녁 20시)"
  ],
  "hashtag_optimization": [
    "브랜드해시태그: #크루즈닷 #크루즈여행 #크루즈상품 (자체 통제 가능, 팔로워에게 유도)",
    "상품해시태그: #싱가포르크루즈 #카리브해크루즈 #지중해크루즈 (지역별/기항지별)",
    "감정해시태그: #여행의꿈 #50대60대여행 #가족여행 #신혼여행 (페르소나별)",
    "계절해시태그: #겨울항공권 #봄시즌크루즈 #여름휴가 #가을여행 (계절연동)",
    "믹스전략: 1게시물당 20-25개 해시태그(인기5+니치15+브랜드5) 조합으로 리치극대화",
    "위치태그: 국내(서울/부산/인천항)/국외(싱가포르/홍콩/더블린) 크루즈출발지/기항지 명시"
  ],
  "shopping_features": [
    "쇼핑탭활성화: 인스타그램 비즈니스 계정 → 쇼핑탭 → Catalog 연동(크루즈닷몰 상품연계)",
    "태그쇼핑: 캐러셀/릴스 각 프레임에 '싱가포르3박 $1,299' 상품태그 삽입(구매욕구 즉시활성화)",
    "컬렉션기능: '50대여행' '신혼부부' '골드멤버십' 별 컬렉션 구성으로 구매경로단축",
    "프로모션배너: 한정판매/조기예약/단체할인 쇼핑탭상단 배너로 노출(CTA극대화)",
    "가격제시: 기본상품가격+할인가 명시 → 팔로워 장바구니저장 → SMS재타겟팅 연동"
  ],
  "memory_content": "크루즈 인스타그램 마케팅 5단계 프레임워크: (1)계정최적화-비즈니스계정+지사별세분화+프로필링크랜딩, (2)콘텐츠7일차시간표-릴스(매일)+스토리(시간별)+캐러셀(주3)+라이브(주1)+게시물(교육영상), (3)해시태그40개혼합-상품+지역+감정+계절해시 브랜드통제, (4)쇼핑탭연동-태그쇼핑+컬렉션+프로모배너로 구매경로2단계감소, (5)세그먼트별카피-50대(안전성/편안함)+신혼(낭만/추억)+전문직(자유/여유) 페르소나별 메시지 맞춤형. 핵심지표: 저장수(장기관심도)+댓글(신뢰도)+클릭(구매의도)로 관리, 주간리뷰 알리고API+페이앱CRM으로 자동추적."
}
